<?xml version="1.0" encoding="UTF-8"?>
<objects serializationModel="Studio.02.02.00">
	<object class="AudioFile" id="{1ca9d468-027c-423b-b4ff-7b79e17b311c}">
		<property name="assetPath">
			<value>SFXPacks/50_CC0_Sci_Fi-SFX/weird_03.ogg</value>
		</property>
		<property name="frequencyInKHz">
			<value>44.0999985</value>
		</property>
		<property name="channelCount">
			<value>2</value>
		</property>
		<property name="length">
			<value>0.96163265306122447</value>
		</property>
		<relationship name="masterAssetFolder">
			<destination>{3ecf0baa-ff82-448b-8700-33ca9125eaef}</destination>
		</relationship>
	</object>
</objects>
