<?xml version="1.0" encoding="UTF-8"?>
<objects serializationModel="Studio.02.02.00">
	<object class="AudioFile" id="{f9ef707d-e2a0-4b28-b405-25c88ae3fcb5}">
		<property name="assetPath">
			<value>UI Sound Library - LittleRobotSoundFactory - CC-BY3/Mp3/Slide_Sharp_01.mp3</value>
		</property>
		<property name="frequencyInKHz">
			<value>44.0999985</value>
		</property>
		<property name="channelCount">
			<value>2</value>
		</property>
		<property name="length">
			<value>0.36571428571428571</value>
		</property>
		<relationship name="masterAssetFolder">
			<destination>{3ecf0baa-ff82-448b-8700-33ca9125eaef}</destination>
		</relationship>
	</object>
</objects>
